fusion_logger_python/__init__.py
fusion_logger_python/core.py
fusion_logger_python/defs.py
fusion_logger_python/processors.py
fusion_logger_python-1.1.1.dist-info/METADATA
fusion_logger_python-1.1.1.dist-info/WHEEL
fusion_logger_python-1.1.1.dist-info/licenses/LICENSE
fusion_logger_python-1.1.1.dist-info/RECORD
