Metadata-Version: 2.4
Name: fusion_logger_python
Version: 1.1.1
Summary:     Fusion Logger is a centralized logging framework that provides configurable log     levels and dynamic scopes for fine-grained control over application logging. It     features structured log records, flexible template-based formatting via tokens,     and a fluent builder for easy logger configuration.     
Project-URL: Homepage, https://github.com/FusionLogger/FusionLogger-Python
Project-URL: Documentation, https://github.com/FusionLogger/FusionLogger-Python/wiki
Project-URL: Repository, https://github.com/FusionLogger/FusionLogger-Python
Project-URL: Issues, https://github.com/FusionLogger/FusionLogger-Python/issues
Project-URL: Changelog, https://github.com/FusionLogger/FusionLogger-Python/releases
Author-email: Lasse-Leander Hillen <lassehillen@gmx.de>
Maintainer-email: Lasse-Leander Hillen <lassehillen@gmx.de>
License-Expression: MIT
License-File: LICENSE
Keywords: formatting,logging
Classifier: Development Status :: 4 - Beta
Classifier: Intended Audience :: Developers
Classifier: Operating System :: OS Independent
Classifier: Programming Language :: Python :: 3
Requires-Python: >=3.8
Requires-Dist: colorama
